simple_pypi_statistics
