Metadata-Version: 1.1
Name: simple-pypi-statistics
Version: 0.1.2
Summary: API and commandline for fetching simple statistics from PyPi's API
Home-page: https://github.com/benjaoming/simple-pypi-statistics
Author: Benjamin Bach
Author-email: benjamin@overtag.dk
License: GPLv2
Keywords: simple_pypi_statistics
Platform: UNKNOWN
Classifier: Development Status :: 4 - Beta
Classifier: Intended Audience :: Developers
Classifier: License :: OSI Approved :: GNU General Public License v2 (GPLv2)
Classifier: Natural Language :: English
Classifier: Programming Language :: Python :: 2
Classifier: Programming Language :: Python :: 2.6
Classifier: Programming Language :: Python :: 2.7
Classifier: Programming Language :: Python :: 3
Classifier: Programming Language :: Python :: 3.3
Classifier: Programming Language :: Python :: 3.4
